toolkit/__init__.py
toolkit/py.typed
toolkit/utils.py
toolkit/graphing/__init__.py
toolkit/test/__init__.py
toolkit/typing/__init__.py
toolkit/typing/si.py
pybox_toolkit-0.1.10.dist-info/METADATA
pybox_toolkit-0.1.10.dist-info/WHEEL
pybox_toolkit-0.1.10.dist-info/top_level.txt
pybox_toolkit-0.1.10.dist-info/RECORD
